{
  "version": "1.0",
  "notes": "Seed priors and trait links for SportSync. Numbers are tunable. Guards apply safety/consistency rules.",
  "priors": {
    "tactical_immersive_combat": 0.07,
    "stealth_flow_missions": 0.06,
    "mind_trap_puzzles": 0.05,
    "range_precision_circuit": 0.05,
    "grip_balance_ascent": 0.05,

    "archery": 0.07,
    "marksmanship": 0.05,
    "climbing": 0.05,
    "swimming": 0.07,
    "distance_running": 0.06,

    "tennis": 0.05,
    "yoga": 0.05,
    "free_diving": 0.04,
    "chess": 0.06,
    "esports": 0.06,

    "football": 0.06,
    "basketball": 0.06,

    "skydiving": 0.02,
    "wingsuit": 0.01,
    "parkour": 0.02
  },

  "trait_links": {
    "introvert": {
      "swimming": 0.6,
      "distance_running": 0.6,
      "tennis": 0.25,
      "chess": 0.7,
      "esports": 0.5,
      "yoga": 0.4,
      "free_diving": 0.4,
      "football": -0.55,
      "basketball": -0.55
    },
    "extrovert": {
      "football": 0.8,
      "basketball": 0.8,
      "tennis": 0.2,
      "chess": -0.5,
      "esports": -0.4
    },
    "precision": {
      "archery": 0.9,
      "marksmanship": 0.8,
      "climbing": 0.5,
      "range_precision_circuit": 0.6,
      "chess": 0.3
    },
    "sustained_attention": {
      "chess": 0.6,
      "esports": 0.7,
      "distance_running": 0.25,
      "archery": 0.25
    },
    "sensation_seeking": {
      "skydiving": 0.9,
      "wingsuit": 0.9,
      "parkour": 0.4,
      "climbing": 0.3,
      "free_diving": 0.2
    },
    "calm_regulation": {
      "free_diving": 0.7,
      "yoga": 0.6,
      "range_precision_circuit": 0.4
    },
    "tactical_mindset": {
      "tactical_immersive_combat": 0.9,
      "stealth_flow_missions": 0.7,
      "mind_trap_puzzles": 0.5,
      "archery": 0.2
    },
    "likes_puzzles": {
      "mind_trap_puzzles": 0.9,
      "chess": 0.7,
      "esports": 0.4
    },
    "prefers_solo": {
      "stealth_flow_missions": 0.6,
      "range_precision_circuit": 0.5,
      "archery": 0.5,
      "marksmanship": 0.4,
      "climbing": 0.3,
      "yoga": 0.3
    },
    "prefers_team": {
      "football": 0.7,
      "basketball": 0.7,
      "tennis": 0.25,
      "tactical_immersive_combat": 0.25
    },
    "anxious": {
      "skydiving": -0.85,
      "wingsuit": -0.85,
      "parkour": -0.3,
      "marksmanship": -0.15
    },
    "low_repetition_tolerance": {
      "tactical_immersive_combat": 0.6,
      "stealth_flow_missions": 0.5,
      "esports": 0.25
    },
    "needs_quick_wins": {
      "range_precision_circuit": 0.5,
      "archery": 0.4,
      "tactical_immersive_combat": 0.3
    },
    "vr_inclination": {
      "tactical_immersive_combat": 0.8,
      "stealth_flow_missions": 0.6,
      "mind_trap_puzzles": 0.6,
      "esports": 0.4
    }
  },

  "guards": {
    "no_high_risk_for_anxiety": true,
    "high_risk_sports": ["skydiving", "wingsuit", "basejump"],
    "avoid_generic_labels": true,
    "forbidden_generic_labels": [
      "impressive compact",
      "impressive-compact",
      "generic sport",
      "sport identity",
      "movement flow",
      "basic flow",
      "simple flow",
      "body flow"
    ]
  },

  "label_aliases": {
    "tactical_immersive_combat": ["tactical immersive combat", "tic", "قتال تكتيكي غامر"],
    "stealth_flow_missions": ["stealth flow missions", "sfm", "مهام تخفّي"],
    "mind_trap_puzzles": ["mind trap puzzles in motion", "mtp", "ألغاز حركة"],
    "range_precision_circuit": ["precision circuit", "rpc", "دقة مدى"],
    "grip_balance_ascent": ["grip & balance ascent", "gba", "قبضة وتوازن"],

    "climbing": ["climb", "bouldering", "تسلق"],
    "archery": ["الرماية بالقوس", "bow"],
    "marksmanship": ["shooting sport (safe range)", "تصويب آمن"],
    "swimming": ["سباحة"],
    "distance_running": ["running", "ركض مسافات"],
    "tennis": ["تنس"],
    "yoga": ["يوجا", "يوغا"],
    "free_diving": ["free diving", "غوص حر"],
    "chess": ["شطرنج"],
    "esports": ["اي سبورت"],
    "football": ["soccer", "كرة قدم"],
    "basketball": ["كرة سلة"],
    "skydiving": ["سكاى دايف"],
    "wingsuit": ["وينج سوت"],
    "parkour": ["باركور"]
  },

  "z_intent_keywords": {
    "ar": {
      "VR": ["vr","واقع افتراضي","افتراضي","نظاره"],
      "تكتيكي": ["تكتيك","تكتيكي","كمين","خطة","خطة لعبة","ambush","tactic"],
      "قتالي": ["قتال","مبارزة","اشتباك","combat"],
      "هدوء/تنفّس": ["هدوء","تنفس","تنفّس","صفاء","تركيز","breath","calm"],
      "أدرينالين": ["اندفاع","أدرينالين","سرعة","انقضاض","strike","fast"],
      "فردي": ["فردي","لوحدي","وحيد","solo"],
      "جماعي": ["جماعي","فريق","team","group"],
      "ألغاز/خداع": ["لغز","الغاز","خدعة","puzzle","feint","خدعه بصريه"],
      "دقة/تصويب": ["دقة","تصويب","نشان","precision","mark"],
      "تخفّي": ["تخفّي","ظل","stealth"],
      "قبضة/توازن": ["قبضة","توازن","grip","balance","climb","تسلق"]
    },
    "en": {
      "VR": ["vr","virtual reality","headset"],
      "Tactical": ["tactic","tactical","ambush","plan"],
      "Combat": ["combat","duel","engage"],
      "Calm/Breath": ["calm","breath","breathing","quiet","focus"],
      "Adrenaline": ["adrenaline","fast","burst","strike","rush"],
      "Solo": ["solo","alone","individual"],
      "Team": ["team","group","co-op","squad"],
      "Puzzles/Feint": ["puzzle","riddle","feint","trick"],
      "Precision": ["precision","aim","mark","accuracy"],
      "Stealth": ["stealth","shadow","hide"],
      "Grip/Balance": ["grip","balance","hold","climb"]
    }
  }
}
